dsgp4/__init__.py
dsgp4/initl.py
dsgp4/mldsgp4.py
dsgp4/newton_method.py
dsgp4/plot.py
dsgp4/sgp4.py
dsgp4/sgp4_batched.py
dsgp4/sgp4init.py
dsgp4/sgp4init_batch.py
dsgp4/tle.py
dsgp4/util.py
dsgp4-1.1.5.dist-info/LICENSE
dsgp4-1.1.5.dist-info/METADATA
dsgp4-1.1.5.dist-info/WHEEL
dsgp4-1.1.5.dist-info/top_level.txt
dsgp4-1.1.5.dist-info/RECORD
